adafruit_ads7830/ads7830.py
adafruit_ads7830/analog_in.py
adafruit_circuitpython_ads7830-1.0.6.dist-info/licenses/LICENSE
adafruit_circuitpython_ads7830-1.0.6.dist-info/METADATA
adafruit_circuitpython_ads7830-1.0.6.dist-info/WHEEL
adafruit_circuitpython_ads7830-1.0.6.dist-info/top_level.txt
adafruit_circuitpython_ads7830-1.0.6.dist-info/RECORD
